pneuma/__init__.py
pneuma/pneuma.py
pneuma/scratch.py
pneuma/index_generator/__init__.py
pneuma/index_generator/index_generator.py
pneuma/query/__init__.py
pneuma/query/query.py
pneuma/registration/__init__.py
pneuma/registration/registration.py
pneuma/registration/scratch.py
pneuma/summarizer/__init__.py
pneuma/summarizer/pipeline_initializer.py
pneuma/summarizer/prompting_interface.py
pneuma/summarizer/summarizer.py
pneuma/utils/__init__.py
pneuma/utils/response.py
pneuma/utils/seed.py
pneuma/utils/table_status.py
pneuma_wip-0.0.3.post5.dist-info/METADATA
pneuma_wip-0.0.3.post5.dist-info/WHEEL
pneuma_wip-0.0.3.post5.dist-info/entry_points.txt
pneuma_wip-0.0.3.post5.dist-info/top_level.txt
pneuma_wip-0.0.3.post5.dist-info/RECORD
