Metadata-Version: 2.1
Name: pneuma_wip
Version: 0.0.3.post5
Summary: Pneuma is a Python package for indexing and querying tables.
Home-page: https://github.com/TheDataStation/Pneuma
Author: University of Chicago
Author-email: davidalexander@uchicago.edu
License: TODO License
Requires-Dist: accelerate ==0.33.0
Requires-Dist: annotated-types ==0.7.0
Requires-Dist: anyio ==4.4.0
Requires-Dist: asgiref ==3.8.1
Requires-Dist: backoff ==2.2.1
Requires-Dist: bcrypt ==4.2.0
Requires-Dist: build ==1.2.1
Requires-Dist: cachetools ==5.4.0
Requires-Dist: certifi ==2024.7.4
Requires-Dist: charset-normalizer ==3.3.2
Requires-Dist: chroma-hnswlib ==0.7.6
Requires-Dist: chromadb ==0.5.5
Requires-Dist: click ==8.1.7
Requires-Dist: colorama ==0.4.6
Requires-Dist: coloredlogs ==15.0.1
Requires-Dist: Deprecated ==1.2.14
Requires-Dist: dnspython ==2.6.1
Requires-Dist: duckdb ==1.0.0
Requires-Dist: email-validator ==2.2.0
Requires-Dist: exceptiongroup ==1.2.2
Requires-Dist: fastapi ==0.111.1
Requires-Dist: fastapi-cli ==0.0.4
Requires-Dist: filelock ==3.15.4
Requires-Dist: fire ==0.6.0
Requires-Dist: flatbuffers ==24.3.25
Requires-Dist: fsspec ==2024.6.1
Requires-Dist: google-auth ==2.32.0
Requires-Dist: googleapis-common-protos ==1.63.2
Requires-Dist: grpcio ==1.65.1
Requires-Dist: h11 ==0.14.0
Requires-Dist: httpcore ==1.0.5
Requires-Dist: httptools ==0.6.1
Requires-Dist: httpx ==0.27.0
Requires-Dist: huggingface-hub ==0.24.2
Requires-Dist: humanfriendly ==10.0
Requires-Dist: idna ==3.7
Requires-Dist: importlib-metadata ==8.0.0
Requires-Dist: importlib-resources ==6.4.0
Requires-Dist: inquirerpy ==0.3.4
Requires-Dist: Jinja2 ==3.1.4
Requires-Dist: joblib ==1.4.2
Requires-Dist: kubernetes ==30.1.0
Requires-Dist: markdown-it-py ==3.0.0
Requires-Dist: MarkupSafe ==2.1.5
Requires-Dist: mdurl ==0.1.2
Requires-Dist: mmh3 ==4.1.0
Requires-Dist: monotonic ==1.6
Requires-Dist: mpmath ==1.3.0
Requires-Dist: networkx ==3.3
Requires-Dist: numpy ==1.26.4
Requires-Dist: oauthlib ==3.2.2
Requires-Dist: onnxruntime ==1.18.1
Requires-Dist: opentelemetry-api ==1.26.0
Requires-Dist: opentelemetry-exporter-otlp-proto-common ==1.26.0
Requires-Dist: opentelemetry-exporter-otlp-proto-grpc ==1.26.0
Requires-Dist: opentelemetry-instrumentation ==0.47b0
Requires-Dist: opentelemetry-instrumentation-asgi ==0.47b0
Requires-Dist: opentelemetry-instrumentation-fastapi ==0.47b0
Requires-Dist: opentelemetry-proto ==1.26.0
Requires-Dist: opentelemetry-sdk ==1.26.0
Requires-Dist: opentelemetry-semantic-conventions ==0.47b0
Requires-Dist: opentelemetry-util-http ==0.47b0
Requires-Dist: orjson ==3.10.6
Requires-Dist: overrides ==7.7.0
Requires-Dist: packaging ==24.1
Requires-Dist: pandas ==2.2.2
Requires-Dist: pfzy ==0.3.4
Requires-Dist: pillow ==10.4.0
Requires-Dist: posthog ==3.5.0
Requires-Dist: prompt-toolkit ==3.0.47
Requires-Dist: protobuf ==4.25.4
Requires-Dist: psutil ==6.0.0
Requires-Dist: pyasn1 ==0.6.0
Requires-Dist: pyasn1-modules ==0.4.0
Requires-Dist: pydantic ==2.8.2
Requires-Dist: pydantic-core ==2.20.1
Requires-Dist: Pygments ==2.18.0
Requires-Dist: PyPika ==0.48.9
Requires-Dist: pyproject-hooks ==1.1.0
Requires-Dist: pyreadline3 ==3.4.1
Requires-Dist: python-dateutil ==2.9.0.post0
Requires-Dist: python-dotenv ==1.0.1
Requires-Dist: python-multipart ==0.0.9
Requires-Dist: pytz ==2024.1
Requires-Dist: PyYAML ==6.0.1
Requires-Dist: regex ==2024.7.24
Requires-Dist: requests ==2.32.3
Requires-Dist: requests-oauthlib ==2.0.0
Requires-Dist: rich ==13.7.1
Requires-Dist: rsa ==4.9
Requires-Dist: safetensors ==0.4.3
Requires-Dist: scikit-learn ==1.5.1
Requires-Dist: scipy ==1.14.0
Requires-Dist: sentence-transformers ==3.0.1
Requires-Dist: shellingham ==1.5.4
Requires-Dist: six ==1.16.0
Requires-Dist: sniffio ==1.3.1
Requires-Dist: starlette ==0.37.2
Requires-Dist: sympy ==1.13.1
Requires-Dist: tenacity ==8.5.0
Requires-Dist: termcolor ==2.4.0
Requires-Dist: threadpoolctl ==3.5.0
Requires-Dist: tokenizers ==0.19.1
Requires-Dist: tomli ==2.0.1
Requires-Dist: torch ==2.2.0
Requires-Dist: tqdm ==4.66.4
Requires-Dist: transformers ==4.43.2
Requires-Dist: typer ==0.12.3
Requires-Dist: typing-extensions ==4.12.2
Requires-Dist: tzdata ==2024.1
Requires-Dist: urllib3 ==2.2.2
Requires-Dist: uvicorn ==0.30.3
Requires-Dist: watchfiles ==0.22.0
Requires-Dist: wcwidth ==0.2.13
Requires-Dist: websocket-client ==1.8.0
Requires-Dist: websockets ==12.0
Requires-Dist: wrapt ==1.16.0
Requires-Dist: zipp ==3.19.2
